{"id":"deimos","name":"Deïmos","englishName":"Deimos","isPlanet":false,"moons":null,"semimajorAxis":23458,"perihelion":23456,"aphelion":23471,"eccentricity":0.0002,"inclination":1.075,"mass":{"massValue":2.4,"massExponent":15},"vol":{"volValue":9.9978,"volExponent":3},"density":1.75,"gravity":0.003,"escape":5.556,"meanRadius":33.0,"equaRadius":7.8,"polarRadius":5.1,"flattening":0,"dimension":"15.0 × 12 × 10.4 ","sideralOrbit":1.26244,"sideralRotation":30.29856,"aroundPlanet":{"planet":"mars","rel":"https://api.le-systeme-solaire.net/rest/bodies/mars"},"discoveredBy":"Asaph Hall","discoveryDate":"12/08/1877","alternativeName":"","axialTilt":0,"avgTemp":0,"mainAnomaly":0,"argPeriapsis":0,"longAscNode":0}